opentv/Preprocessor.py
opentv/RobotController.py
opentv/TeleVision.py
opentv/__init__.py
opentv/constants/__init__.py
opentv/constants/constants_avp.py
opentv/constants/constants_vuer.py
opentv/dynamixel/__init__.py
opentv/dynamixel/active_cam.py
opentv/dynamixel/agent.py
opentv/dynamixel/driver.py
opentv/dynamixel/dynamixel_robot.py
opentv/dynamixel/robot.py
opentv/motion/__init__.py
opentv/motion/pink_motion_control.py
opentv/motion/pinocchio_base.py
opentv/motion/pinocchio_motion_control_casadi.py
opentv/motion/pinocchio_motion_control_clik.py
opentv/motion/pinocchio_motion_retarget.py
opentv/motion/pinocchio_motion_retarget_jax.py
opentv/utils/__init__.py
opentv/utils/camera_utils.py
opentv/utils/motion_utils.py
opentv/webrtc/__init__.py
opentv/webrtc/zed_server.py
opentv-0.1.2.dist-info/METADATA
opentv-0.1.2.dist-info/WHEEL
opentv-0.1.2.dist-info/top_level.txt
opentv-0.1.2.dist-info/RECORD
