Metadata-Version: 2.1
Name: opentv
Version: 0.1.2
Summary: teleoperation for all kinds of robots remotely or locally with immersive VR
Author: Xuxin Cheng, Jialong Li, etc.
Requires-Dist: vuer==0.0.35rc18
Requires-Dist: numpy
Requires-Dist: pin
Requires-Dist: nlopt
Requires-Dist: aiohttp
Requires-Dist: aiohttp-cors
Requires-Dist: pytransform3d
Requires-Dist: pyyaml
Requires-Dist: pynput
Requires-Dist: aiortc
